{
  "_fv": 43,
  "_type": "recipe",
  "definition": {
    "recipeType": "Crafting",
    "recipeRetstackSize": 1,
    "group": "",
    "cookingBookCategory": "MISC",
    "xpReward": 0.0,
    "cookingTime": 200,
    "craftingBookCategory": "MISC",
    "recipeShapeless": false,
    "recipeSlots": [
      {
        "value": "CUSTOM:WhiteGlichBlock"
      },
      {
        "value": "CUSTOM:WhiteGlichBlock"
      },
      {
        "value": "CUSTOM:WhiteGlichBlock"
      },
      {
        "value": "CUSTOM:ForgedHotSteelT9"
      },
      {
        "value": "CUSTOM:ClockworkScytheT0"
      },
      {
        "value": "CUSTOM:ForgedHotSteelT9"
      },
      {
        "value": "CUSTOM:WhiteGlichBlock"
      },
      {
        "value": "CUSTOM:ForgedHotSteelT9"
      },
      {
        "value": "CUSTOM:ForgedHotSteelT9"
      }
    ],
    "recipeReturnStack": {
      "value": "CUSTOM:ClockworkScytheT1"
    },
    "name": "clockwork_scythe_t_1_recipe",
    "namespace": "mod"
  }
}