{
  "_fv": 43,
  "_type": "tool",
  "definition": {
    "renderType": 0,
    "texture": "quartz_sword",
    "customModelName": "Normal",
    "name": "Quartz Sword",
    "specialInfo": [],
    "creativeTab": {
      "value": "COMBAT"
    },
    "toolType": "Sword",
    "harvestLevel": 4,
    "efficiency": 10.0,
    "attackSpeed": 1.0,
    "enchantability": 31,
    "damageVsEntity": 4.0,
    "usageCount": 754,
    "blocksAffected": [],
    "hasGlow": false,
    "repairItems": [
      {
        "value": "Items.QUARTZ"
      }
    ],
    "immuneToFire": false,
    "stayInGridWhenCrafting": false,
    "damageOnCrafting": false
  }
}